Metadata-Version: 1.1
Name: matchkraft
Version: 0.0.2
Summary: Fuzzy match company names
Home-page: UNKNOWN
Author: Rene Tatua Castillo
Author-email: info@matchkraft.com
License: MIT
Keywords: matchkraft,machine learning,python
Platform: UNKNOWN
Classifier: Development Status :: 5 - Production/Stable
Classifier: Operating System :: Microsoft :: Windows :: Windows 10
Classifier: License :: OSI Approved :: MIT License
Classifier: Programming Language :: Python :: 3
